[[0.078958,{"lines":{"0":[["root@ns:/tmp#                                                                                                                                                ",{}]],"1":[["                                                                                                                                                             ",{}]],"2":[["                                                                                                                                                             ",{}]],"3":[["                                                                                                                                                             ",{}]],"4":[["                                                                                                                                                             ",{}]],"5":[["                                                                                                                                                             ",{}]],"6":[["                                                                                                                                                             ",{}]],"7":[["                                                                                                                                                             ",{}]],"8":[["                                                                                                                                                             ",{}]],"9":[["                                                                                                                                                             ",{}]],"10":[["                                                                                                                                                             ",{}]],"11":[["                                                                                                                                                             ",{}]],"12":[["                                                                                                                                                             ",{}]],"13":[["                                                                                                                                                             ",{}]],"14":[["                                                                                                                                                             ",{}]],"15":[["                                                                                                                                                             ",{}]],"16":[["                                                                                                                                                             ",{}]],"17":[["                                                                                                                                                             ",{}]],"18":[["                                                                                                                                                             ",{}]],"19":[["                                                                                                                                                             ",{}]],"20":[["                                                                                                                                                             ",{}]],"21":[["                                                                                                                                                             ",{}]],"22":[["                                                                                                                                                             ",{}]],"23":[["                                                                                                                                                             ",{}]],"24":[["                                                                                                                                                             ",{}]],"25":[["                                                                                                                                                             ",{}]],"26":[["                                                                                                                                                             ",{}]],"27":[["                                                                                                                                                             ",{}]],"28":[["                                                                                                                                                             ",{}]],"29":[["                                                                                                                                                             ",{}]],"30":[["                                                                                                                                                             ",{}]],"31":[["                                                                                                                                                             ",{}]],"32":[["                                                                                                                                                             ",{}]],"33":[["                                                                                                                                                             ",{}]],"34":[["                                                                                                                                                             ",{}]],"35":[["                                                                                                                                                             ",{}]],"36":[["                                                                                                                                                             ",{}]],"37":[["                                                                                                                                                             ",{}]],"38":[["                                                                                                                                                             ",{}]],"39":[["                                                                                                                                                             ",{}]],"40":[["                                                                                                                                                             ",{}]],"41":[["                                                                                                                                                             ",{}]],"42":[["                                                                                                                                                             ",{}]],"43":[["                                                                                                                                                             ",{}]],"44":[["                                                                                                                                                             ",{}]],"45":[["                                                                                                                                                             ",{}]],"46":[["                                                                                                                                                             ",{}]],"47":[["                                                                                                                                                             ",{}]],"48":[["                                                                                                                                                             ",{}]],"49":[["                                                                                                                                                             ",{}]],"50":[["                                                                                                                                                             ",{}]],"51":[["                                                                                                                                                             ",{}]],"52":[["                                                                                                                                                             ",{}]],"53":[["                                                                                                                                                             ",{}]],"54":[["                                                                                                                                                             ",{}]],"55":[["                                                                                                                                                             ",{}]],"56":[["                                                                                                                                                             ",{}]],"57":[["                                                                                                                                                             ",{}]]},"cursor":{"x":14,"y":0,"visible":true}}],[3.195663,{"lines":{"0":[["root@ns:/tmp# e                                                                                                                                              ",{}]]},"cursor":{"x":15}}],[0.27654,{"lines":{"0":[["root@ns:/tmp# ec                                                                                                                                             ",{}]]},"cursor":{"x":16}}],[0.280648,{"lines":{"0":[["root@ns:/tmp# ech                                                                                                                                            ",{}]]},"cursor":{"x":17}}],[0.139568,{"lines":{"0":[["root@ns:/tmp# echo                                                                                                                                           ",{}]]},"cursor":{"x":18}}],[0.168264,{"cursor":{"x":19}}],[0.788347,{"lines":{"0":[["root@ns:/tmp# echo 1                                                                                                                                         ",{}]]},"cursor":{"x":20}}],[0.381015,{"cursor":{"x":21}}],[0.551548,{"lines":{"0":[["root@ns:/tmp# echo 1 >                                                                                                                                       ",{}]]},"cursor":{"x":22}}],[0.222721,{"cursor":{"x":23}}],[0.180004,{"lines":{"0":[["root@ns:/tmp# echo 1 > /                                                                                                                                     ",{}]]},"cursor":{"x":24}}],[0.581813,{"lines":{"0":[["root@ns:/tmp# echo 1 > /t                                                                                                                                    ",{}]]},"cursor":{"x":25}}],[0.342298,{"lines":{"0":[["root@ns:/tmp# echo 1 > /tm                                                                                                                                   ",{}]]},"cursor":{"x":26}}],[0.212344,{"lines":{"0":[["root@ns:/tmp# echo 1 > /tmp                                                                                                                                  ",{}]]},"cursor":{"x":27}}],[0.361497,{"lines":{"0":[["root@ns:/tmp# echo 1 > /tmp/                                                                                                                                 ",{}]]},"cursor":{"x":28}}],[0.365329,{"lines":{"0":[["root@ns:/tmp# echo 1 > /tmp/1                                                                                                                                ",{}]]},"cursor":{"x":29}}],[2.872425,{"lines":{"1":[["bash: /tmp/1: Это каталог                                                                                                                                    ",{}]],"2":[["root@ns:/tmp#                                                                                                                                                ",{}]]},"cursor":{"x":14,"y":2}}],[2.569941,{"lines":{"2":[["root@ns:/tmp# exit                                                                                                                                           ",{}]]},"cursor":{"x":0,"y":3}}]]