[[0.002734,{"lines":{"0":[["$                                                                               ",{}]],"1":[["                                                                                ",{}]],"2":[["                                                                                ",{}]],"3":[["                                                                                ",{}]],"4":[["                                                                                ",{}]],"5":[["                                                                                ",{}]],"6":[["                                                                                ",{}]],"7":[["                                                                                ",{}]],"8":[["                                                                                ",{}]],"9":[["                                                                                ",{}]],"10":[["                                                                                ",{}]],"11":[["                                                                                ",{}]],"12":[["                                                                                ",{}]],"13":[["                                                                                ",{}]],"14":[["                                                                                ",{}]],"15":[["                                                                                ",{}]],"16":[["                                                                                ",{}]],"17":[["                                                                                ",{}]],"18":[["                                                                                ",{}]],"19":[["                                                                                ",{}]],"20":[["                                                                                ",{}]],"21":[["                                                                                ",{}]],"22":[["                                                                                ",{}]],"23":[["                                                                                ",{}]]},"cursor":{"x":2,"y":0,"visible":true}}],[1.167282,{"lines":{"0":[["$ p                                                                             ",{}]]},"cursor":{"x":3}}],[0.184012,{"lines":{"0":[["$ ph                                                                            ",{}]]},"cursor":{"x":4}}],[0.119786,{"lines":{"0":[["$ php                                                                           ",{}]]},"cursor":{"x":5}}],[0.288156,{"cursor":{"x":6}}],[0.5517570000000001,{"lines":{"0":[["$ php i                                                                         ",{}]]},"cursor":{"x":7}}],[0.056339,{"lines":{"0":[["$ php in                                                                        ",{}]]},"cursor":{"x":8}}],[0.399571,{"lines":{"0":[["$ php in_                                                                       ",{}]]},"cursor":{"x":9}}],[0.408277,{"lines":{"0":[["$ php in_o                                                                      ",{}]]},"cursor":{"x":10}}],[0.199725,{"lines":{"0":[["$ php in_ou                                                                     ",{}]]},"cursor":{"x":11}}],[0.095966,{"lines":{"0":[["$ php in_out                                                                    ",{}]]},"cursor":{"x":12}}],[0.208402,{"lines":{"0":[["$ php in_out.                                                                   ",{}]]},"cursor":{"x":13}}],[0.247671,{"lines":{"0":[["$ php in_out.p                                                                  ",{}]]},"cursor":{"x":14}}],[0.104426,{"lines":{"0":[["$ php in_out.ph                                                                 ",{}]]},"cursor":{"x":15}}],[0.09537,{"lines":{"0":[["$ php in_out.php                                                                ",{}]]},"cursor":{"x":16}}],[0.272131,{"cursor":{"x":0,"y":1}}],[0.872457,{"lines":{"1":[["T                                                                               ",{}]]},"cursor":{"x":1}}],[0.167534,{"lines":{"1":[["Th                                                                              ",{}]]},"cursor":{"x":2}}],[0.159921,{"lines":{"1":[["Thi                                                                             ",{}]]},"cursor":{"x":3}}],[0.104027,{"lines":{"1":[["This                                                                            ",{}]]},"cursor":{"x":4}}],[0.159989,{"cursor":{"x":5}}],[0.184027,{"lines":{"1":[["This w                                                                          ",{}]]},"cursor":{"x":6}}],[0.240135,{"lines":{"1":[["This wa                                                                         ",{}]]},"cursor":{"x":7}}],[0.111407,{"lines":{"1":[["This was                                                                        ",{}]]},"cursor":{"x":8}}],[0.120585,{"cursor":{"x":9}}],[0.111955,{"lines":{"1":[["This was a                                                                      ",{}]]},"cursor":{"x":10}}],[0.120296,{"cursor":{"x":11}}],[0.303582,{"lines":{"1":[["This was a t                                                                    ",{}]]},"cursor":{"x":12}}],[0.231887,{"lines":{"1":[["This was a tr                                                                   ",{}]]},"cursor":{"x":13}}],[0.095972,{"lines":{"1":[["This was a tri                                                                  ",{}]]},"cursor":{"x":14}}],[0.151662,{"lines":{"1":[["This was a triu                                                                 ",{}]]},"cursor":{"x":15}}],[0.18429,{"lines":{"1":[["This was a trium                                                                ",{}]]},"cursor":{"x":16}}],[0.200118,{"lines":{"1":[["This was a triump                                                               ",{}]]},"cursor":{"x":17}}],[0.320034,{"lines":{"1":[["This was a triumph                                                              ",{}]]},"cursor":{"x":18}}],[0.319521,{"lines":{"1":[["This was a triumph!                                                             ",{}]]},"cursor":{"x":19}}],[0.01656,{"lines":{"1":[["This was a triumph!~                                                            ",{}]]},"cursor":{"x":20}}],[0.60053,{"lines":{"1":[["This was a triumph!                                                             ",{}]]},"cursor":{"x":19}}],[0.246911,{"cursor":{"x":0,"y":2}}],[0.000221,{"lines":{"2":[["This was a triumph!                                                             ",{}]]},"cursor":{"y":3}}],[1.023941,{"lines":{"3":[["I                                                                               ",{}]]},"cursor":{"x":1}}],[0.45593,{"lines":{"3":[["I'                                                                              ",{}]]},"cursor":{"x":2}}],[0.543768,{"lines":{"3":[["I'm                                                                             ",{}]]},"cursor":{"x":3}}],[0.136471,{"cursor":{"x":4}}],[0.231861,{"lines":{"3":[["I'm m                                                                           ",{}]]},"cursor":{"x":5}}],[0.119666,{"lines":{"3":[["I'm ma                                                                          ",{}]]},"cursor":{"x":6}}],[0.104211,{"lines":{"3":[["I'm mak                                                                         ",{}]]},"cursor":{"x":7}}],[0.216064,{"lines":{"3":[["I'm maki                                                                        ",{}]]},"cursor":{"x":8}}],[0.06414599999999999,{"lines":{"3":[["I'm makin                                                                       ",{}]]},"cursor":{"x":9}}],[0.087782,{"lines":{"3":[["I'm making                                                                      ",{}]]},"cursor":{"x":10}}],[0.10403,{"cursor":{"x":11}}],[0.119929,{"lines":{"3":[["I'm making a                                                                    ",{}]]},"cursor":{"x":12}}],[0.103773,{"cursor":{"x":13}}],[0.128238,{"lines":{"3":[["I'm making a n                                                                  ",{}]]},"cursor":{"x":14}}],[0.167929,{"lines":{"3":[["I'm making a no                                                                 ",{}]]},"cursor":{"x":15}}],[0.072146,{"lines":{"3":[["I'm making a not                                                                ",{}]]},"cursor":{"x":16}}],[0.071941,{"lines":{"3":[["I'm making a note                                                               ",{}]]},"cursor":{"x":17}}],[0.135972,{"cursor":{"x":18}}],[0.183756,{"lines":{"3":[["I'm making a note h                                                             ",{}]]},"cursor":{"x":19}}],[0.120022,{"lines":{"3":[["I'm making a note he                                                            ",{}]]},"cursor":{"x":20}}],[0.128266,{"lines":{"3":[["I'm making a note her                                                           ",{}]]},"cursor":{"x":21}}],[0.071823,{"lines":{"3":[["I'm making a note here                                                          ",{}]]},"cursor":{"x":22}}],[0.344128,{"lines":{"3":[["I'm making a note here:                                                         ",{}]]},"cursor":{"x":23}}],[0.8641,{"cursor":{"x":0,"y":4}}],[0.000532,{"lines":{"4":[["I'm making a note here:                                                         ",{}]]},"cursor":{"y":5}}],[0.775474,{"lines":{"5":[["H                                                                               ",{}]]},"cursor":{"x":1}}],[0.09593599999999999,{"lines":{"5":[["Hu                                                                              ",{}]]},"cursor":{"x":2}}],[0.111833,{"lines":{"5":[["Hug                                                                             ",{}]]},"cursor":{"x":3}}],[0.064079,{"lines":{"5":[["Huge                                                                            ",{}]]},"cursor":{"x":4}}],[0.08763600000000001,{"cursor":{"x":5}}],[0.41608,{"lines":{"5":[["Huge S                                                                          ",{}]]},"cursor":{"x":6}}],[0.143716,{"lines":{"5":[["Huge Su                                                                         ",{}]]},"cursor":{"x":7}}],[0.112251,{"lines":{"5":[["Huge Suc                                                                        ",{}]]},"cursor":{"x":8}}],[0.176383,{"lines":{"5":[["Huge Succ                                                                       ",{}]]},"cursor":{"x":9}}],[0.103477,{"lines":{"5":[["Huge Succe                                                                      ",{}]]},"cursor":{"x":10}}],[0.247905,{"lines":{"5":[["Huge Succes                                                                     ",{}]]},"cursor":{"x":11}}],[0.144007,{"lines":{"5":[["Huge Success                                                                    ",{}]]},"cursor":{"x":12}}],[0.559993,{"lines":{"5":[["Huge Success!                                                                   ",{}]]},"cursor":{"x":13}}],[0.672024,{"cursor":{"x":0,"y":6}}],[0.0005,{"lines":{"6":[["Huge Success!                                                                   ",{}]]},"cursor":{"y":7}}],[1.487573,{"lines":{"7":[["^C                                                                              ",{}]]},"cursor":{"x":2}}],[0.002637,{"lines":{"8":[["$ sh: turning off NDELAY mode                                                   ",{}]]},"cursor":{"x":0,"y":9}}],[0.685021,{"lines":{"9":[["e                                                                               ",{}]]},"cursor":{"x":1}}],[0.192066,{"lines":{"9":[["ex                                                                              ",{}]]},"cursor":{"x":2}}],[0.104418,{"lines":{"9":[["exi                                                                             ",{}]]},"cursor":{"x":3}}],[0.135295,{"lines":{"9":[["exit                                                                            ",{}]]},"cursor":{"x":4}}],[0.112289,{"cursor":{"x":0,"y":10}}]]