[[0.345389,{"lines":{"0":[["                                                                                            ",{}]],"1":[["                                                                                            ",{}]],"2":[["                                                                                            ",{}]],"3":[["                                                                                            ",{}]],"4":[["                                                                                            ",{}]],"5":[["                                                                                            ",{}]],"6":[["                                                                                            ",{}]],"7":[["                                                                                            ",{}]],"8":[["                                                                                            ",{}]],"9":[["                                                                                            ",{}]],"10":[["                                                                                            ",{}]],"11":[["                                                                                            ",{}]],"12":[["                                                                                            ",{}]],"13":[["                                                                                            ",{}]],"14":[["                                                                                            ",{}]],"15":[["                                                                                            ",{}]],"16":[["                                                                                            ",{}]],"17":[["                                                                                            ",{}]],"18":[["                                                                                            ",{}]],"19":[["                                                                                            ",{}]],"20":[["                                                                                            ",{}]],"21":[["                                                                                            ",{}]],"22":[["                                                                                            ",{}]],"23":[["                                                                                            ",{}]],"24":[["                                                                                            ",{}]],"25":[["                                                                                            ",{}]],"26":[["                                                                                            ",{}]],"27":[["                                                                                            ",{}]]},"cursor":{"x":0,"y":0,"visible":true}}],[0.000134,{}],[0.100214,{"lines":{"1":[["~",{"fg":4}],["                                                                                           ",{}]],"2":[["▶                                                                                           ",{}]]},"cursor":{"x":2,"y":2}}],[0.000137,{}],[0.913394,{"lines":{"2":[["▶ c                                                                                         ",{}]]},"cursor":{"x":3}}],[0.094205,{"lines":{"2":[["▶ cl                                                                                        ",{}]]},"cursor":{"x":4}}],[0.112106,{"lines":{"2":[["▶ cle                                                                                       ",{}]]},"cursor":{"x":5}}],[0.06342299999999999,{"lines":{"2":[["▶ clea                                                                                      ",{}]]},"cursor":{"x":6}}],[0.072725,{"lines":{"2":[["▶ clear                                                                                     ",{}]]},"cursor":{"x":7}}],[0.095655,{}],[0.009642999999999999,{"lines":{"1":[["                                                                                            ",{}]],"2":[["                                                                                            ",{}]]},"cursor":{"x":0,"y":0}}],[0.07972600000000001,{"lines":{"1":[["~",{"fg":4}],["                                                                                           ",{}]],"2":[["▶                                                                                           ",{}]]},"cursor":{"x":2,"y":2}}],[0.000103,{}],[0.22307,{"lines":{"2":[["▶ c                                                                                         ",{}]]},"cursor":{"x":3}}],[0.039107,{"lines":{"2":[["▶ cd                                                                                        ",{}]]},"cursor":{"x":4}}],[0.05666,{"cursor":{"x":5}}],[0.391835,{"lines":{"2":[["▶ cd /                                                                                      ",{}]]},"cursor":{"x":6}}],[0.247887,{"lines":{"2":[["▶ cd /t                                                                                     ",{}]]},"cursor":{"x":7}}],[0.128176,{"lines":{"2":[["▶ cd /tm                                                                                    ",{}]]},"cursor":{"x":8}}],[0.11185,{"lines":{"2":[["▶ cd /tmp                                                                                   ",{}]]},"cursor":{"x":9}}],[0.343818,{}],[0.001951,{"cursor":{"x":0,"y":3}}],[0.070649,{"lines":{"4":[["/private/tmp",{"fg":4}],["                                                                                ",{}]],"5":[["▶                                                                                           ",{}]]},"cursor":{"x":2,"y":5}}],[0.000113,{}],[0.848031,{"lines":{"5":[["▶ m                                                                                         ",{}]]},"cursor":{"x":3}}],[0.06376800000000001,{"lines":{"5":[["▶ mk                                                                                        ",{}]]},"cursor":{"x":4}}],[0.07177699999999999,{"lines":{"5":[["▶ mkd                                                                                       ",{}]]},"cursor":{"x":5}}],[0.127599,{"lines":{"5":[["▶ mkdi                                                                                      ",{}]]},"cursor":{"x":6}}],[0.08849899999999999,{"lines":{"5":[["▶ mkdir                                                                                     ",{}]]},"cursor":{"x":7}}],[0.239565,{"cursor":{"x":8}}],[1.504036,{"lines":{"5":[["▶ mkdir y                                                                                   ",{}]]},"cursor":{"x":9}}],[0.049667,{"lines":{"5":[["▶ mkdir yo                                                                                  ",{}]]},"cursor":{"x":10}}],[0.09468699999999999,{}],[0.005992999999999999,{"cursor":{"x":0,"y":6}}],[0.06943100000000001,{"lines":{"7":[["/private/tmp",{"fg":4}],["                                                                                ",{}]],"8":[["▶                                                                                           ",{}]]},"cursor":{"x":2,"y":8}}],[0.000122,{}],[0.628737,{"lines":{"8":[["▶ c                                                                                         ",{}]]},"cursor":{"x":3}}],[0.095475,{"lines":{"8":[["▶ cd                                                                                        ",{}]]},"cursor":{"x":4}}],[0.047293,{"cursor":{"x":5}}],[0.25659,{"lines":{"8":[["▶ cd y                                                                                      ",{}]]},"cursor":{"x":6}}],[0.063871,{"lines":{"8":[["▶ cd yo                                                                                     ",{}]]},"cursor":{"x":7}}],[0.143973,{}],[0.002498,{"cursor":{"x":0,"y":9}}],[0.07061099999999999,{"lines":{"10":[["/private/tmp/yo",{"fg":4}],["                                                                             ",{}]],"11":[["▶                                                                                           ",{}]]},"cursor":{"x":2,"y":11}}],[0.000107,{}],[0.143689,{"lines":{"11":[["▶ c                                                                                         ",{}]]},"cursor":{"x":3}}],[0.135328,{"lines":{"11":[["▶ cl                                                                                        ",{}]]},"cursor":{"x":4}}],[0.087369,{"lines":{"11":[["▶ cle                                                                                       ",{}]]},"cursor":{"x":5}}],[0.079357,{"lines":{"11":[["▶ clea                                                                                      ",{}]]},"cursor":{"x":6}}],[0.056125,{"lines":{"11":[["▶ clear                                                                                     ",{}]]},"cursor":{"x":7}}],[0.105312,{}],[0.005761,{"lines":{"1":[["                                                                                            ",{}]],"2":[["                                                                                            ",{}]],"4":[["                                                                                            ",{}]],"5":[["                                                                                            ",{}]],"7":[["                                                                                            ",{}]],"8":[["                                                                                            ",{}]],"10":[["                                                                                            ",{}]],"11":[["                                                                                            ",{}]]},"cursor":{"x":0,"y":0}}],[0.081374,{"lines":{"1":[["/private/tmp/yo",{"fg":4}],["                                                                             ",{}]],"2":[["▶                                                                                           ",{}]]},"cursor":{"x":2,"y":2}}],[9.500000000000001e-05,{}],[1.79321,{"lines":{"2":[["▶ w                                                                                         ",{}]]},"cursor":{"x":3}}],[0.191305,{"lines":{"2":[["▶ wg                                                                                        ",{}]]},"cursor":{"x":4}}],[0.103989,{"lines":{"2":[["▶ wge                                                                                       ",{}]]},"cursor":{"x":5}}],[0.047343,{"lines":{"2":[["▶ wget                                                                                      ",{}]]},"cursor":{"x":6}}],[0.128327,{"cursor":{"x":7}}],[0.219309,{"lines":{"2":[["▶ wget h                                                                                    ",{}]]},"cursor":{"x":8}}],[0.005313000000000001,{"lines":{"2":[["▶ wget https://github.com/toin0u/yo-cli/releases/download/1.0.0/yo.phar                     ",{}]]},"cursor":{"x":71}}],[0.679325,{"cursor":{"x":72}}],[0.104449,{"lines":{"2":[["▶ wget https://github.com/toin0u/yo-cli/releases/download/1.0.0/yo.phar -                   ",{}]]},"cursor":{"x":73}}],[0.144122,{"lines":{"2":[["▶ wget https://github.com/toin0u/yo-cli/releases/download/1.0.0/yo.phar -q                  ",{}]]},"cursor":{"x":74}}],[0.24764,{}],[0.001631,{"cursor":{"x":0,"y":3}}],[3.466819,{}],[0.000135,{}],[0.068426,{"lines":{"4":[["/private/tmp/yo",{"fg":4}],["                                                                             ",{}]],"5":[["▶                                                                                           ",{}]]},"cursor":{"x":2,"y":5}}],[9.8e-05,{}],[1.079695,{"lines":{"5":[["▶ l                                                                                         ",{}]]},"cursor":{"x":3}}],[0.032838,{"lines":{"5":[["▶ ll                                                                                        ",{}]]},"cursor":{"x":4}}],[0.054878,{}],[0.005862000000000001,{"lines":{"6":[["total 1440                                                                                  ",{}]],"7":[["-rw-r--r--  1 antoine  wheel   719K Feb  1 22:31 yo.phar                                    ",{}]]},"cursor":{"x":0,"y":8}}],[0.070062,{"lines":{"9":[["/private/tmp/yo",{"fg":4}],["                                                                             ",{}]],"10":[["▶                                                                                           ",{}]]},"cursor":{"x":2,"y":10}}],[0.000132,{}],[1.261614,{"lines":{"10":[["▶ p                                                                                         ",{}]]},"cursor":{"x":3}}],[0.150169,{"lines":{"10":[["▶ ph                                                                                        ",{}]]},"cursor":{"x":4}}],[0.096361,{"lines":{"10":[["▶ php                                                                                       ",{}]]},"cursor":{"x":5}}],[0.136614,{"cursor":{"x":6}}],[0.392174,{"lines":{"10":[["▶ php y                                                                                     ",{}]]},"cursor":{"x":7}}],[0.079511,{"lines":{"10":[["▶ php yo                                                                                    ",{}]]},"cursor":{"x":8}}],[0.208618,{"lines":{"10":[["▶ php yo.                                                                                   ",{}]]},"cursor":{"x":9}}],[0.196879,{"lines":{"10":[["▶ php yo.phar",{}],[" ",{"bold":true}],["                                                                              ",{}]]},"cursor":{"x":14}}],[1.258788,{"lines":{"10":[["▶ php yo.phar                                                                               ",{}]]},"cursor":{"x":13}}],[0.001236,{"cursor":{"x":0,"y":11}}],[0.047675,{"lines":{"11":[["PHP Fatal error:  Uncaught exception 'PharException' with message 'phar \"/private/tmp/yo/yo.",{}]],"12":[["phar\" openssl signature could not be verified: openssl public key could not be read' in /pri",{}]],"13":[["vate/tmp/yo/yo.phar:9                                                                       ",{}]],"14":[["Stack trace:                                                                                ",{}]],"15":[["#0 /private/tmp/yo/yo.phar(9): Phar::mapPhar('default.phar')                                ",{}]],"16":[["#1 {main}                                                                                   ",{}]],"17":[["  thrown in /private/tmp/yo/yo.phar on line 9                                               ",{}]]},"cursor":{"y":18}}],[0.005602000000000001,{"lines":{"2":[["▶ ll                                                                                        ",{}]],"3":[["total 1440                                                                                  ",{}]],"4":[["-rw-r--r--  1 antoine  wheel   719K Feb  1 22:31 yo.phar                                    ",{}]],"5":[["                                                                                            ",{}]],"6":[["/private/tmp/yo",{"fg":4}],["                                                                             ",{}]],"7":[["▶ php yo.phar                                                                               ",{}]],"8":[["PHP Fatal error:  Uncaught exception 'PharException' with message 'phar \"/private/tmp/yo/yo.",{}]],"9":[["phar\" openssl signature could not be verified: openssl public key could not be read' in /pri",{}]],"10":[["vate/tmp/yo/yo.phar:9                                                                       ",{}]],"11":[["Stack trace:                                                                                ",{}]],"12":[["#0 /private/tmp/yo/yo.phar(9): Phar::mapPhar('default.phar')                                ",{}]],"13":[["#1 {main}                                                                                   ",{}]],"14":[["  thrown in /private/tmp/yo/yo.phar on line 9                                               ",{}]],"15":[["                                                                                            ",{}]],"16":[["Fatal error: Uncaught exception 'PharException' with message 'phar \"/private/tmp/yo/yo.phar\"",{}]],"17":[[" openssl signature could not be verified: openssl public key could not be read' in /private/",{}]],"18":[["tmp/yo/yo.phar on line 9                                                                    ",{}]],"20":[["PharException: phar \"/private/tmp/yo/yo.phar\" openssl signature could not be verified: opens",{}]],"21":[["sl public key could not be read in /private/tmp/yo/yo.phar on line 9                        ",{}]],"23":[["Call Stack:                                                                                 ",{}]],"24":[["    0.0004     233840   1. {main}() /private/tmp/yo/yo.phar:0                               ",{}]],"25":[["    0.0005     233936   2. Phar::mapPhar() /private/tmp/yo/yo.phar:9                        ",{}]]},"cursor":{"y":27}}],[0.072002,{"lines":{"0":[["▶ ll                                                                                        ",{}]],"1":[["total 1440                                                                                  ",{}]],"2":[["-rw-r--r--  1 antoine  wheel   719K Feb  1 22:31 yo.phar                                    ",{}]],"3":[["                                                                                            ",{}]],"4":[["/private/tmp/yo",{"fg":4}],["                                                                             ",{}]],"5":[["▶ php yo.phar                                                                               ",{}]],"6":[["PHP Fatal error:  Uncaught exception 'PharException' with message 'phar \"/private/tmp/yo/yo.",{}]],"7":[["phar\" openssl signature could not be verified: openssl public key could not be read' in /pri",{}]],"8":[["vate/tmp/yo/yo.phar:9                                                                       ",{}]],"9":[["Stack trace:                                                                                ",{}]],"10":[["#0 /private/tmp/yo/yo.phar(9): Phar::mapPhar('default.phar')                                ",{}]],"11":[["#1 {main}                                                                                   ",{}]],"12":[["  thrown in /private/tmp/yo/yo.phar on line 9                                               ",{}]],"13":[["                                                                                            ",{}]],"14":[["Fatal error: Uncaught exception 'PharException' with message 'phar \"/private/tmp/yo/yo.phar\"",{}]],"15":[[" openssl signature could not be verified: openssl public key could not be read' in /private/",{}]],"16":[["tmp/yo/yo.phar on line 9                                                                    ",{}]],"17":[["                                                                                            ",{}]],"18":[["PharException: phar \"/private/tmp/yo/yo.phar\" openssl signature could not be verified: opens",{}]],"19":[["sl public key could not be read in /private/tmp/yo/yo.phar on line 9                        ",{}]],"20":[["                                                                                            ",{}]],"21":[["Call Stack:                                                                                 ",{}]],"22":[["    0.0004     233840   1. {main}() /private/tmp/yo/yo.phar:0                               ",{}]],"23":[["    0.0005     233936   2. Phar::mapPhar() /private/tmp/yo/yo.phar:9                        ",{}]],"24":[["                                                                                            ",{}]],"25":[["                                                                                            ",{}]],"26":[["/private/tmp/yo",{"fg":4}],["                                                                             ",{}]],"27":[["▶                                                                                           ",{}]]},"cursor":{"x":2}}],[0.000126,{"lines":{"26":[["/private/tmp/yo",{"fg":4}],["                                                                           ",{}],["⍉",{"fg":1}],[" ",{}]]}}],[1.210162,{"lines":{"27":[["▶ php yo.phar                                                                               ",{}]]},"cursor":{"x":13}}],[0.407251,{"lines":{"27":[["▶ ll                                                                                        ",{}]]},"cursor":{"x":4}}],[0.343963,{"lines":{"27":[["▶ wget https://github.com/toin0u/yo-cli/releases/download/1.0.0/yo.phar -q                  ",{}]]},"cursor":{"x":74}}],[1.160024,{"cursor":{"x":73}}],[0.224213,{"cursor":{"x":72}}],[0.183826,{"cursor":{"x":71}}],[0.559646,{"lines":{"27":[["▶ wget https://github.com/toin0u/yo-cli/releases/download/1.0.0/yo.phar. -q                 ",{}]]},"cursor":{"x":72}}],[0.344392,{"lines":{"27":[["▶ wget https://github.com/toin0u/yo-cli/releases/download/1.0.0/yo.phar.p -q                ",{}]]},"cursor":{"x":73}}],[0.095806,{"lines":{"27":[["▶ wget https://github.com/toin0u/yo-cli/releases/download/1.0.0/yo.phar.pu -q               ",{}]]},"cursor":{"x":74}}],[0.216038,{"lines":{"27":[["▶ wget https://github.com/toin0u/yo-cli/releases/download/1.0.0/yo.phar.pub -q              ",{}]]},"cursor":{"x":75}}],[0.152025,{"lines":{"27":[["▶ wget https://github.com/toin0u/yo-cli/releases/download/1.0.0/yo.phar.pubk -q             ",{}]]},"cursor":{"x":76}}],[0.127957,{"lines":{"27":[["▶ wget https://github.com/toin0u/yo-cli/releases/download/1.0.0/yo.phar.pubke -q            ",{}]]},"cursor":{"x":77}}],[0.10399,{"lines":{"27":[["▶ wget https://github.com/toin0u/yo-cli/releases/download/1.0.0/yo.phar.pubkey -q           ",{}]]},"cursor":{"x":78}}],[0.57604,{}],[0.00152,{"lines":{"0":[["total 1440                                                                                  ",{}]],"1":[["-rw-r--r--  1 antoine  wheel   719K Feb  1 22:31 yo.phar                                    ",{}]],"2":[["                                                                                            ",{}]],"3":[["/private/tmp/yo",{"fg":4}],["                                                                             ",{}]],"4":[["▶ php yo.phar                                                                               ",{}]],"5":[["PHP Fatal error:  Uncaught exception 'PharException' with message 'phar \"/private/tmp/yo/yo.",{}]],"6":[["phar\" openssl signature could not be verified: openssl public key could not be read' in /pri",{}]],"7":[["vate/tmp/yo/yo.phar:9                                                                       ",{}]],"8":[["Stack trace:                                                                                ",{}]],"9":[["#0 /private/tmp/yo/yo.phar(9): Phar::mapPhar('default.phar')                                ",{}]],"10":[["#1 {main}                                                                                   ",{}]],"11":[["  thrown in /private/tmp/yo/yo.phar on line 9                                               ",{}]],"12":[["                                                                                            ",{}]],"13":[["Fatal error: Uncaught exception 'PharException' with message 'phar \"/private/tmp/yo/yo.phar\"",{}]],"14":[[" openssl signature could not be verified: openssl public key could not be read' in /private/",{}]],"15":[["tmp/yo/yo.phar on line 9                                                                    ",{}]],"16":[["                                                                                            ",{}]],"17":[["PharException: phar \"/private/tmp/yo/yo.phar\" openssl signature could not be verified: opens",{}]],"18":[["sl public key could not be read in /private/tmp/yo/yo.phar on line 9                        ",{}]],"19":[["                                                                                            ",{}]],"20":[["Call Stack:                                                                                 ",{}]],"21":[["    0.0004     233840   1. {main}() /private/tmp/yo/yo.phar:0                               ",{}]],"22":[["    0.0005     233936   2. Phar::mapPhar() /private/tmp/yo/yo.phar:9                        ",{}]],"23":[["                                                                                            ",{}]],"25":[["/private/tmp/yo",{"fg":4}],["                                                                           ",{}],["⍉",{"fg":1}],[" ",{}]],"26":[["▶ wget https://github.com/toin0u/yo-cli/releases/download/1.0.0/yo.phar.pubkey -q           ",{}]],"27":[["                                                                                            ",{}]]},"cursor":{"x":0}}],[1.72577,{}],[0.000227,{}],[0.071826,{"lines":{"0":[["                                                                                            ",{}]],"1":[["/private/tmp/yo",{"fg":4}],["                                                                             ",{}]],"2":[["▶ php yo.phar                                                                               ",{}]],"3":[["PHP Fatal error:  Uncaught exception 'PharException' with message 'phar \"/private/tmp/yo/yo.",{}]],"4":[["phar\" openssl signature could not be verified: openssl public key could not be read' in /pri",{}]],"5":[["vate/tmp/yo/yo.phar:9                                                                       ",{}]],"6":[["Stack trace:                                                                                ",{}]],"7":[["#0 /private/tmp/yo/yo.phar(9): Phar::mapPhar('default.phar')                                ",{}]],"8":[["#1 {main}                                                                                   ",{}]],"9":[["  thrown in /private/tmp/yo/yo.phar on line 9                                               ",{}]],"10":[["                                                                                            ",{}]],"11":[["Fatal error: Uncaught exception 'PharException' with message 'phar \"/private/tmp/yo/yo.phar\"",{}]],"12":[[" openssl signature could not be verified: openssl public key could not be read' in /private/",{}]],"13":[["tmp/yo/yo.phar on line 9                                                                    ",{}]],"14":[["                                                                                            ",{}]],"15":[["PharException: phar \"/private/tmp/yo/yo.phar\" openssl signature could not be verified: opens",{}]],"16":[["sl public key could not be read in /private/tmp/yo/yo.phar on line 9                        ",{}]],"17":[["                                                                                            ",{}]],"18":[["Call Stack:                                                                                 ",{}]],"19":[["    0.0004     233840   1. {main}() /private/tmp/yo/yo.phar:0                               ",{}]],"20":[["    0.0005     233936   2. Phar::mapPhar() /private/tmp/yo/yo.phar:9                        ",{}]],"21":[["                                                                                            ",{}]],"22":[["                                                                                            ",{}]],"23":[["/private/tmp/yo",{"fg":4}],["                                                                           ",{}],["⍉",{"fg":1}],[" ",{}]],"24":[["▶ wget https://github.com/toin0u/yo-cli/releases/download/1.0.0/yo.phar.pubkey -q           ",{}]],"25":[["                                                                                            ",{}]],"26":[["/private/tmp/yo",{"fg":4}],["                                                                             ",{}]],"27":[["▶                                                                                           ",{}]]},"cursor":{"x":2}}],[8.500000000000001e-05,{}],[0.56111,{"lines":{"27":[["▶ wget https://github.com/toin0u/yo-cli/releases/download/1.0.0/yo.phar.pubkey -q           ",{}]]},"cursor":{"x":81}}],[0.175438,{"lines":{"27":[["▶ php yo.phar                                                                               ",{}]]},"cursor":{"x":13}}],[0.599948,{}],[0.001555,{"lines":{"0":[["/private/tmp/yo",{"fg":4}],["                                                                             ",{}]],"1":[["▶ php yo.phar                                                                               ",{}]],"2":[["PHP Fatal error:  Uncaught exception 'PharException' with message 'phar \"/private/tmp/yo/yo.",{}]],"3":[["phar\" openssl signature could not be verified: openssl public key could not be read' in /pri",{}]],"4":[["vate/tmp/yo/yo.phar:9                                                                       ",{}]],"5":[["Stack trace:                                                                                ",{}]],"6":[["#0 /private/tmp/yo/yo.phar(9): Phar::mapPhar('default.phar')                                ",{}]],"7":[["#1 {main}                                                                                   ",{}]],"8":[["  thrown in /private/tmp/yo/yo.phar on line 9                                               ",{}]],"9":[["                                                                                            ",{}]],"10":[["Fatal error: Uncaught exception 'PharException' with message 'phar \"/private/tmp/yo/yo.phar\"",{}]],"11":[[" openssl signature could not be verified: openssl public key could not be read' in /private/",{}]],"12":[["tmp/yo/yo.phar on line 9                                                                    ",{}]],"13":[["                                                                                            ",{}]],"14":[["PharException: phar \"/private/tmp/yo/yo.phar\" openssl signature could not be verified: opens",{}]],"15":[["sl public key could not be read in /private/tmp/yo/yo.phar on line 9                        ",{}]],"16":[["                                                                                            ",{}]],"17":[["Call Stack:                                                                                 ",{}]],"18":[["    0.0004     233840   1. {main}() /private/tmp/yo/yo.phar:0                               ",{}]],"19":[["    0.0005     233936   2. Phar::mapPhar() /private/tmp/yo/yo.phar:9                        ",{}]],"20":[["                                                                                            ",{}]],"22":[["/private/tmp/yo",{"fg":4}],["                                                                           ",{}],["⍉",{"fg":1}],[" ",{}]],"23":[["▶ wget https://github.com/toin0u/yo-cli/releases/download/1.0.0/yo.phar.pubkey -q           ",{}]],"24":[["                                                                                            ",{}]],"25":[["/private/tmp/yo",{"fg":4}],["                                                                             ",{}]],"26":[["▶ php yo.phar                                                                               ",{}]],"27":[["                                                                                            ",{}]]},"cursor":{"x":0}}],[0.075252,{"lines":{"0":[["PHP Fatal error:  Uncaught exception 'PharException' with message 'phar \"/private/tmp/yo/yo.",{}]],"1":[["phar\" openssl signature could not be verified: openssl public key could not be read' in /pri",{}]],"2":[["vate/tmp/yo/yo.phar:9                                                                       ",{}]],"3":[["Stack trace:                                                                                ",{}]],"4":[["#0 /private/tmp/yo/yo.phar(9): Phar::mapPhar('default.phar')                                ",{}]],"5":[["#1 {main}                                                                                   ",{}]],"6":[["  thrown in /private/tmp/yo/yo.phar on line 9                                               ",{}]],"7":[["                                                                                            ",{}]],"8":[["Fatal error: Uncaught exception 'PharException' with message 'phar \"/private/tmp/yo/yo.phar\"",{}]],"9":[[" openssl signature could not be verified: openssl public key could not be read' in /private/",{}]],"10":[["tmp/yo/yo.phar on line 9                                                                    ",{}]],"11":[["                                                                                            ",{}]],"12":[["PharException: phar \"/private/tmp/yo/yo.phar\" openssl signature could not be verified: opens",{}]],"13":[["sl public key could not be read in /private/tmp/yo/yo.phar on line 9                        ",{}]],"14":[["                                                                                            ",{}]],"15":[["Call Stack:                                                                                 ",{}]],"16":[["    0.0004     233840   1. {main}() /private/tmp/yo/yo.phar:0                               ",{}]],"17":[["    0.0005     233936   2. Phar::mapPhar() /private/tmp/yo/yo.phar:9                        ",{}]],"18":[["                                                                                            ",{}]],"19":[["                                                                                            ",{}]],"20":[["/private/tmp/yo",{"fg":4}],["                                                                           ",{}],["⍉",{"fg":1}],[" ",{}]],"21":[["▶ wget https://github.com/toin0u/yo-cli/releases/download/1.0.0/yo.phar.pubkey -q           ",{}]],"22":[["                                                                                            ",{}]],"23":[["/private/tmp/yo",{"fg":4}],["                                                                             ",{}]],"24":[["▶ php yo.phar                                                                               ",{}]],"25":[["Yo",{"fg":2}],[" version ",{}],["1.0.0",{"fg":3}],["                                                                            ",{}]],"26":[["                                                                                            ",{}]]}}],[0.010747,{"lines":{"0":[["                                                                                            ",{}]],"1":[["/private/tmp/yo",{"fg":4}],["                                                                             ",{}]],"2":[["▶ php yo.phar                                                                               ",{}]],"3":[["Yo",{"fg":2}],[" version ",{}],["1.0.0",{"fg":3}],["                                                                            ",{}]],"4":[["                                                                                            ",{}]],"5":[["Usage:",{"fg":3}],["                                                                                      ",{}]],"6":[[" [options] command [arguments]                                                              ",{}]],"8":[["Options:",{"fg":3}],["                                                                                    ",{}]],"9":[[" ",{}],["--help",{"fg":2}],[" (-h)           Display this help message                                            ",{}]],"10":[[" ",{}],["--quiet",{"fg":2}],[" (-q)          Do not output any message                                            ",{}]],"11":[[" ",{}],["--verbose",{"fg":2}],[" (-v|vv|vvv) Increase the verbosity of messages: 1 for normal output, 2 for more v",{}]],"12":[["erbose output and 3 for debug                                                               ",{}]],"13":[[" ",{}],["--version",{"fg":2}],[" (-V)        Display this application version                                     ",{}]],"14":[[" ",{}],["--ansi",{"fg":2}],["                Force ANSI output                                                    ",{}]],"15":[[" ",{}],["--no-ansi",{"fg":2}],["             Disable ANSI output                                                  ",{}]],"16":[[" ",{}],["--no-interaction",{"fg":2}],[" (-n) Do not ask any interactive question                                  ",{}]],"17":[[" ",{}],["--config",{"fg":2}],[" (-c)         Specify a custom location for the configuration file                 ",{}]],"19":[["Available commands:",{"fg":3}],["                                                                         ",{}]],"20":[[" ",{}],["all     ",{"fg":2}],[" Yo your subscribers with or without a link                                        ",{}]],"21":[[" ",{}],["check   ",{"fg":2}],[" Check if the username exists or not                                               ",{}]],"22":[[" ",{}],["create  ",{"fg":2}],[" Create an Yo user                                                                 ",{}]],"23":[[" ",{}],["help    ",{"fg":2}],[" Displays help for a command                                                       ",{}]],"24":[[" ",{}],["list    ",{"fg":2}],[" Lists commands                                                                    ",{}]],"25":[[" ",{}],["total   ",{"fg":2}],[" Get the total number of subscribers                                               ",{}]],"26":[[" ",{}],["user    ",{"fg":2}],[" Yo an user with a link, a location or nothing                                     ",{}]]}}],[0.073159,{"lines":{"0":[["▶ php yo.phar                                                                               ",{}]],"1":[["Yo",{"fg":2}],[" version ",{}],["1.0.0",{"fg":3}],["                                                                            ",{}]],"2":[["                                                                                            ",{}]],"3":[["Usage:",{"fg":3}],["                                                                                      ",{}]],"4":[[" [options] command [arguments]                                                              ",{}]],"5":[["                                                                                            ",{}]],"6":[["Options:",{"fg":3}],["                                                                                    ",{}]],"7":[[" ",{}],["--help",{"fg":2}],[" (-h)           Display this help message                                            ",{}]],"8":[[" ",{}],["--quiet",{"fg":2}],[" (-q)          Do not output any message                                            ",{}]],"9":[[" ",{}],["--verbose",{"fg":2}],[" (-v|vv|vvv) Increase the verbosity of messages: 1 for normal output, 2 for more v",{}]],"10":[["erbose output and 3 for debug                                                               ",{}]],"11":[[" ",{}],["--version",{"fg":2}],[" (-V)        Display this application version                                     ",{}]],"12":[[" ",{}],["--ansi",{"fg":2}],["                Force ANSI output                                                    ",{}]],"13":[[" ",{}],["--no-ansi",{"fg":2}],["             Disable ANSI output                                                  ",{}]],"14":[[" ",{}],["--no-interaction",{"fg":2}],[" (-n) Do not ask any interactive question                                  ",{}]],"15":[[" ",{}],["--config",{"fg":2}],[" (-c)         Specify a custom location for the configuration file                 ",{}]],"16":[["                                                                                            ",{}]],"17":[["Available commands:",{"fg":3}],["                                                                         ",{}]],"18":[[" ",{}],["all     ",{"fg":2}],[" Yo your subscribers with or without a link                                        ",{}]],"19":[[" ",{}],["check   ",{"fg":2}],[" Check if the username exists or not                                               ",{}]],"20":[[" ",{}],["create  ",{"fg":2}],[" Create an Yo user                                                                 ",{}]],"21":[[" ",{}],["help    ",{"fg":2}],[" Displays help for a command                                                       ",{}]],"22":[[" ",{}],["list    ",{"fg":2}],[" Lists commands                                                                    ",{}]],"23":[[" ",{}],["total   ",{"fg":2}],[" Get the total number of subscribers                                               ",{}]],"24":[[" ",{}],["user    ",{"fg":2}],[" Yo an user with a link, a location or nothing                                     ",{}]],"25":[["                                                                                            ",{}]],"26":[["/private/tmp/yo",{"fg":4}],["                                                                             ",{}]],"27":[["▶                                                                                           ",{}]]},"cursor":{"x":2}}],[6.1e-05,{}],[1.023787,{"lines":{"27":[["▶ php yo.phar                                                                               ",{}]]},"cursor":{"x":13}}],[0.455216,{"cursor":{"x":14}}],[0.232492,{"lines":{"27":[["▶ php yo.phar c                                                                             ",{}]]},"cursor":{"x":15}}],[0.143645,{"lines":{"27":[["▶ php yo.phar ch                                                                            ",{}]]},"cursor":{"x":16}}],[0.079747,{"lines":{"27":[["▶ php yo.phar che                                                                           ",{}]]},"cursor":{"x":17}}],[0.096205,{"lines":{"27":[["▶ php yo.phar chec                                                                          ",{}]]},"cursor":{"x":18}}],[0.112186,{"lines":{"27":[["▶ php yo.phar check                                                                         ",{}]]},"cursor":{"x":19}}],[0.487861,{"cursor":{"x":20}}],[0.17637,{"lines":{"27":[["▶ php yo.phar check t                                                                       ",{}]]},"cursor":{"x":21}}],[0.111732,{"lines":{"27":[["▶ php yo.phar check to                                                                      ",{}]]},"cursor":{"x":22}}],[0.09528399999999999,{"lines":{"27":[["▶ php yo.phar check toi                                                                     ",{}]]},"cursor":{"x":23}}],[0.064787,{"lines":{"27":[["▶ php yo.phar check toin                                                                    ",{}]]},"cursor":{"x":24}}],[0.183055,{"lines":{"27":[["▶ php yo.phar check toin0                                                                   ",{}]]},"cursor":{"x":25}}],[0.112914,{"lines":{"27":[["▶ php yo.phar check toin0u                                                                  ",{}]]},"cursor":{"x":26}}],[0.551952,{}],[0.001567,{"lines":{"0":[["Yo",{"fg":2}],[" version ",{}],["1.0.0",{"fg":3}],["                                                                            ",{}]],"1":[["                                                                                            ",{}]],"2":[["Usage:",{"fg":3}],["                                                                                      ",{}]],"3":[[" [options] command [arguments]                                                              ",{}]],"4":[["                                                                                            ",{}]],"5":[["Options:",{"fg":3}],["                                                                                    ",{}]],"6":[[" ",{}],["--help",{"fg":2}],[" (-h)           Display this help message                                            ",{}]],"7":[[" ",{}],["--quiet",{"fg":2}],[" (-q)          Do not output any message                                            ",{}]],"8":[[" ",{}],["--verbose",{"fg":2}],[" (-v|vv|vvv) Increase the verbosity of messages: 1 for normal output, 2 for more v",{}]],"9":[["erbose output and 3 for debug                                                               ",{}]],"10":[[" ",{}],["--version",{"fg":2}],[" (-V)        Display this application version                                     ",{}]],"11":[[" ",{}],["--ansi",{"fg":2}],["                Force ANSI output                                                    ",{}]],"12":[[" ",{}],["--no-ansi",{"fg":2}],["             Disable ANSI output                                                  ",{}]],"13":[[" ",{}],["--no-interaction",{"fg":2}],[" (-n) Do not ask any interactive question                                  ",{}]],"14":[[" ",{}],["--config",{"fg":2}],[" (-c)         Specify a custom location for the configuration file                 ",{}]],"15":[["                                                                                            ",{}]],"16":[["Available commands:",{"fg":3}],["                                                                         ",{}]],"17":[[" ",{}],["all     ",{"fg":2}],[" Yo your subscribers with or without a link                                        ",{}]],"18":[[" ",{}],["check   ",{"fg":2}],[" Check if the username exists or not                                               ",{}]],"19":[[" ",{}],["create  ",{"fg":2}],[" Create an Yo user                                                                 ",{}]],"20":[[" ",{}],["help    ",{"fg":2}],[" Displays help for a command                                                       ",{}]],"21":[[" ",{}],["list    ",{"fg":2}],[" Lists commands                                                                    ",{}]],"22":[[" ",{}],["total   ",{"fg":2}],[" Get the total number of subscribers                                               ",{}]],"23":[[" ",{}],["user    ",{"fg":2}],[" Yo an user with a link, a location or nothing                                     ",{}]],"24":[["                                                                                            ",{}]],"25":[["/private/tmp/yo",{"fg":4}],["                                                                             ",{}]],"26":[["▶ php yo.phar check toin0u                                                                  ",{}]],"27":[["                                                                                            ",{}]]},"cursor":{"x":0}}],[1.499711,{"lines":{"27":[["`TOIN0U`",{"fg":3}],["                                                                                    ",{}]]},"cursor":{"x":8}}],[0.007925999999999999,{"lines":{"0":[["                                                                                            ",{}]],"1":[["Usage:",{"fg":3}],["                                                                                      ",{}]],"2":[[" [options] command [arguments]                                                              ",{}]],"3":[["                                                                                            ",{}]],"4":[["Options:",{"fg":3}],["                                                                                    ",{}]],"5":[[" ",{}],["--help",{"fg":2}],[" (-h)           Display this help message                                            ",{}]],"6":[[" ",{}],["--quiet",{"fg":2}],[" (-q)          Do not output any message                                            ",{}]],"7":[[" ",{}],["--verbose",{"fg":2}],[" (-v|vv|vvv) Increase the verbosity of messages: 1 for normal output, 2 for more v",{}]],"8":[["erbose output and 3 for debug                                                               ",{}]],"9":[[" ",{}],["--version",{"fg":2}],[" (-V)        Display this application version                                     ",{}]],"10":[[" ",{}],["--ansi",{"fg":2}],["                Force ANSI output                                                    ",{}]],"11":[[" ",{}],["--no-ansi",{"fg":2}],["             Disable ANSI output                                                  ",{}]],"12":[[" ",{}],["--no-interaction",{"fg":2}],[" (-n) Do not ask any interactive question                                  ",{}]],"13":[[" ",{}],["--config",{"fg":2}],[" (-c)         Specify a custom location for the configuration file                 ",{}]],"14":[["                                                                                            ",{}]],"15":[["Available commands:",{"fg":3}],["                                                                         ",{}]],"16":[[" ",{}],["all     ",{"fg":2}],[" Yo your subscribers with or without a link                                        ",{}]],"17":[[" ",{}],["check   ",{"fg":2}],[" Check if the username exists or not                                               ",{}]],"18":[[" ",{}],["create  ",{"fg":2}],[" Create an Yo user                                                                 ",{}]],"19":[[" ",{}],["help    ",{"fg":2}],[" Displays help for a command                                                       ",{}]],"20":[[" ",{}],["list    ",{"fg":2}],[" Lists commands                                                                    ",{}]],"21":[[" ",{}],["total   ",{"fg":2}],[" Get the total number of subscribers                                               ",{}]],"22":[[" ",{}],["user    ",{"fg":2}],[" Yo an user with a link, a location or nothing                                     ",{}]],"23":[["                                                                                            ",{}]],"24":[["/private/tmp/yo",{"fg":4}],["                                                                             ",{}]],"25":[["▶ php yo.phar check toin0u                                                                  ",{}]],"26":[["`TOIN0U`",{"fg":3}],[" exists.",{}],["%",{"bold":true,"inverse":true}],["                                                                           ",{}]],"27":[["                                                                                            ",{}]]},"cursor":{"x":0}}],[0.06911100000000001,{"lines":{"0":[[" [options] command [arguments]                                                              ",{}]],"1":[["                                                                                            ",{}]],"2":[["Options:",{"fg":3}],["                                                                                    ",{}]],"3":[[" ",{}],["--help",{"fg":2}],[" (-h)           Display this help message                                            ",{}]],"4":[[" ",{}],["--quiet",{"fg":2}],[" (-q)          Do not output any message                                            ",{}]],"5":[[" ",{}],["--verbose",{"fg":2}],[" (-v|vv|vvv) Increase the verbosity of messages: 1 for normal output, 2 for more v",{}]],"6":[["erbose output and 3 for debug                                                               ",{}]],"7":[[" ",{}],["--version",{"fg":2}],[" (-V)        Display this application version                                     ",{}]],"8":[[" ",{}],["--ansi",{"fg":2}],["                Force ANSI output                                                    ",{}]],"9":[[" ",{}],["--no-ansi",{"fg":2}],["             Disable ANSI output                                                  ",{}]],"10":[[" ",{}],["--no-interaction",{"fg":2}],[" (-n) Do not ask any interactive question                                  ",{}]],"11":[[" ",{}],["--config",{"fg":2}],[" (-c)         Specify a custom location for the configuration file                 ",{}]],"12":[["                                                                                            ",{}]],"13":[["Available commands:",{"fg":3}],["                                                                         ",{}]],"14":[[" ",{}],["all     ",{"fg":2}],[" Yo your subscribers with or without a link                                        ",{}]],"15":[[" ",{}],["check   ",{"fg":2}],[" Check if the username exists or not                                               ",{}]],"16":[[" ",{}],["create  ",{"fg":2}],[" Create an Yo user                                                                 ",{}]],"17":[[" ",{}],["help    ",{"fg":2}],[" Displays help for a command                                                       ",{}]],"18":[[" ",{}],["list    ",{"fg":2}],[" Lists commands                                                                    ",{}]],"19":[[" ",{}],["total   ",{"fg":2}],[" Get the total number of subscribers                                               ",{}]],"20":[[" ",{}],["user    ",{"fg":2}],[" Yo an user with a link, a location or nothing                                     ",{}]],"21":[["                                                                                            ",{}]],"22":[["/private/tmp/yo",{"fg":4}],["                                                                             ",{}]],"23":[["▶ php yo.phar check toin0u                                                                  ",{}]],"24":[["`TOIN0U`",{"fg":3}],[" exists.",{}],["%",{"bold":true,"inverse":true}],["                                                                           ",{}]],"25":[["                                                                                            ",{}]],"26":[["/private/tmp/yo",{"fg":4}],["                                                                             ",{}]],"27":[["▶                                                                                           ",{}]]},"cursor":{"x":2}}],[0.00013,{}],[2.381933,{"lines":{"0":[["                                                                                            ",{}]],"1":[["Options:",{"fg":3}],["                                                                                    ",{}]],"2":[[" ",{}],["--help",{"fg":2}],[" (-h)           Display this help message                                            ",{}]],"3":[[" ",{}],["--quiet",{"fg":2}],[" (-q)          Do not output any message                                            ",{}]],"4":[[" ",{}],["--verbose",{"fg":2}],[" (-v|vv|vvv) Increase the verbosity of messages: 1 for normal output, 2 for more v",{}]],"5":[["erbose output and 3 for debug                                                               ",{}]],"6":[[" ",{}],["--version",{"fg":2}],[" (-V)        Display this application version                                     ",{}]],"7":[[" ",{}],["--ansi",{"fg":2}],["                Force ANSI output                                                    ",{}]],"8":[[" ",{}],["--no-ansi",{"fg":2}],["             Disable ANSI output                                                  ",{}]],"9":[[" ",{}],["--no-interaction",{"fg":2}],[" (-n) Do not ask any interactive question                                  ",{}]],"10":[[" ",{}],["--config",{"fg":2}],[" (-c)         Specify a custom location for the configuration file                 ",{}]],"11":[["                                                                                            ",{}]],"12":[["Available commands:",{"fg":3}],["                                                                         ",{}]],"13":[[" ",{}],["all     ",{"fg":2}],[" Yo your subscribers with or without a link                                        ",{}]],"14":[[" ",{}],["check   ",{"fg":2}],[" Check if the username exists or not                                               ",{}]],"15":[[" ",{}],["create  ",{"fg":2}],[" Create an Yo user                                                                 ",{}]],"16":[[" ",{}],["help    ",{"fg":2}],[" Displays help for a command                                                       ",{}]],"17":[[" ",{}],["list    ",{"fg":2}],[" Lists commands                                                                    ",{}]],"18":[[" ",{}],["total   ",{"fg":2}],[" Get the total number of subscribers                                               ",{}]],"19":[[" ",{}],["user    ",{"fg":2}],[" Yo an user with a link, a location or nothing                                     ",{}]],"20":[["                                                                                            ",{}]],"21":[["/private/tmp/yo",{"fg":4}],["                                                                             ",{}]],"22":[["▶ php yo.phar check toin0u                                                                  ",{}]],"23":[["`TOIN0U`",{"fg":3}],[" exists.",{}],["%",{"bold":true,"inverse":true}],["                                                                           ",{}]],"24":[["                                                                                            ",{}]],"25":[["/private/tmp/yo",{"fg":4}],["                                                                             ",{}]],"26":[["▶                                                                                           ",{}]],"27":[["                                                                                            ",{}]]},"cursor":{"x":0}}]]